cipher/__init__.py
cipher/cli.py
cipher/container.py
cipher/settings.py
cipher/strategy.py
cipher/system.py
cipher/trader.py
cipher/factories/__init__.py
cipher/factories/stats.py
cipher/models/__init__.py
cipher/models/commission.py
cipher/models/cursor.py
cipher/models/datas.py
cipher/models/interval.py
cipher/models/log_level.py
cipher/models/meta.py
cipher/models/output.py
cipher/models/position.py
cipher/models/session.py
cipher/models/sessions.py
cipher/models/stats.py
cipher/models/template.py
cipher/models/time.py
cipher/models/time_delta.py
cipher/models/transaction.py
cipher/models/transactions.py
cipher/models/wallet.py
cipher/plotters/__init__.py
cipher/plotters/base.py
cipher/plotters/finplot.py
cipher/plotters/mplfinance.py
cipher/proxies/__init__.py
cipher/proxies/session.py
cipher/resources/__init__.py
cipher/resources/logging.py
cipher/services/__init__.py
cipher/services/data.py
cipher/sources/__init__.py
cipher/sources/base.py
cipher/sources/binance_futures_ohlc.py
cipher/sources/binance_spot_ohlc.py
cipher/sources/csv_file.py
cipher/sources/gateio_spot_ohlc.py
cipher/sources/yahoo_finance_ohlc.py
cipher/templates/env.j2
cipher/templates/readme.j2
cipher/templates/strategies/default.j2
cipher/use_cases/__init__.py
cipher/use_cases/create_strategy.py
cipher/use_cases/init_repository.py
cipher/utils/__init__.py
cipher/utils/colors.py
cipher/utils/decimals.py
cipher/utils/environment.py
cipher/utils/rate_limit.py
cipher/values/__init__.py
cipher/values/base.py
cipher/values/percent.py
cipher/values/quote.py
cipher_bt-0.6.8.dist-info/METADATA
cipher_bt-0.6.8.dist-info/WHEEL
cipher_bt-0.6.8.dist-info/entry_points.txt
cipher_bt-0.6.8.dist-info/licenses/LICENSE
cipher_bt-0.6.8.dist-info/RECORD
