Metadata-Version: 2.4
Name: cipher-bt
Version: 0.6.8
Summary: Cipher - Trading Strategy Backtesting Framework.
Project-URL: Homepage, https://cipher.nanvel.com/
Project-URL: Repository, https://github.com/nanvel/cipher-bt
Author-email: Oleksandr Polieno <oleksandr@nanvel.com>
License-File: LICENSE
Keywords: backtest,colab,crypto,framework,quant,strategy,trading
Classifier: Programming Language :: Python :: 3.9
Classifier: Programming Language :: Python :: 3.10
Classifier: Programming Language :: Python :: 3.11
Classifier: Programming Language :: Python :: 3.12
Requires-Python: <3.13,>=3.9
Requires-Dist: dependency-injector>=4.46.0
Requires-Dist: jinja2>=3.1.6
Requires-Dist: mplfinance>=0.12.10b0
Requires-Dist: pydantic-settings>=2.9.1
Requires-Dist: pydantic>=2.11.4
Requires-Dist: requests>=2.32.3
Requires-Dist: tabulate>=0.9.0
Requires-Dist: typer>=0.15.4
Requires-Dist: ujson>=5.10.0
Provides-Extra: finplot
Requires-Dist: finplot<2,>=1.9.0; extra == 'finplot'
Provides-Extra: jupyter
Requires-Dist: jupyterlab<4,>=3.5.2; extra == 'jupyter'
Provides-Extra: talib
Requires-Dist: ta-lib>=0.6.4; extra == 'talib'
Provides-Extra: yfinance
Requires-Dist: yfinance<0.3,>=0.2.3; extra == 'yfinance'
